[
  {
    "title": "Overwatch Halloween",
    "desc": "Lorem ipsum dolor sit amet, consectetur adipisc ing ipsum dolor sit amet, consectetur adipisc ing ipsum dolor sit amet.",
    "imageUrl": "../images/review/5.jpg",
    "imageAlt": "1",
    "review": "9.4"
  },
  {
    "title": "Grand Theft Auto",
    "desc": "Lorem ipsum dolor sit amet, consectetur adipisc ing ipsum dolor sit amet, consectetur adipisc ing ipsum dolor sit amet.",
    "imageUrl": "../images/review/6.jpg",
    "imageAlt": "1",
    "review": "9.4"
  },
  {
    "title": "Avatar",
    "desc": "Lorem ipsum dolor sit amet, consectetur adipisc ing ipsum dolor sit amet, consectetur adipisc ing ipsum dolor sit amet.",
    "imageUrl": "../images/review/7.jpg",
    "imageAlt": "1",
    "review": "9.4"
  },
  {
    "title": "Anthem",
    "desc": "Lorem ipsum dolor sit amet, consectetur adipisc ing ipsum dolor sit amet, consectetur adipisc ing ipsum dolor sit amet.",
    "imageUrl": "../images/review/8.jpg",
    "imageAlt": "1",
    "review": "9.4"
  },
  {
    "title": "Cyberpunk 2077",
    "desc": "Lorem ipsum dolor sit amet, consectetur adipisc ing ipsum dolor sit amet, consectetur adipisc ing ipsum dolor sit amet.",
    "imageUrl": "../images/review/9.jpg",
    "imageAlt": "1",
    "review": "9.4"
  },
  {
    "title": "Spiderman",
    "desc": "Lorem ipsum dolor sit amet, consectetur adipisc ing ipsum dolor sit amet, consectetur adipisc ing ipsum dolor sit amet.",
    "imageUrl": "../images/review/10.jpg",
    "imageAlt": "1",
    "review": "9.4"
  }
]
